{
  "main": {
    "id": "2282e786059d2808",
    "type": "split",
    "children": [
      {
        "id": "b1026d0647ff2d5c",
        "type": "tabs",
        "children": [
          {
            "id": "782a0ab928ab5810",
            "type": "leaf",
            "state": {
              "type": "markdown",
              "state": {
                "file": "History/_History - Map of Contents.md",
                "mode": "source",
                "source": false,
                "backlinks": false
              },
              "icon": "lucide-file",
              "title": "_History - Map of Contents"
            }
          }
        ]
      }
    ],
    "direction": "vertical"
  },
  "left": {
    "id": "1bc7049d1d209b2f",
    "type": "split",
    "children": [
      {
        "id": "8822e85fd1461fa9",
        "type": "tabs",
        "children": [
          {
            "id": "7adb17c520de5016",
            "type": "leaf",
            "state": {
              "type": "file-explorer",
              "state": {
                "sortOrder": "byCreatedTime",
                "autoReveal": false
              },
              "icon": "lucide-folder-closed",
              "title": "Files"
            }
          },
          {
            "id": "9865e682d2a9ebea",
            "type": "leaf",
            "state": {
              "type": "search",
              "state": {
                "query": "",
                "matchingCase": false,
                "explainSearch": false,
                "collapseAll": false,
                "extraContext": false,
                "sortOrder": "alphabetical"
              },
              "icon": "lucide-search",
              "title": "Search"
            }
          },
          {
            "id": "0cc7f2731f058fb8",
            "type": "leaf",
            "state": {
              "type": "bookmarks",
              "state": {},
              "icon": "lucide-bookmark",
              "title": "Bookmarks"
            }
          }
        ]
      }
    ],
    "direction": "horizontal",
    "width": 343.5110321044922
  },
  "right": {
    "id": "9ff74f0d31edc521",
    "type": "split",
    "children": [
      {
        "id": "371e316ae69ebf68",
        "type": "tabs",
        "dimension": 49.307774227902016,
        "children": [
          {
            "id": "1ee66af3cb611110",
            "type": "leaf",
            "state": {
              "type": "graph",
              "state": {},
              "icon": "lucide-git-fork",
              "title": "Graph view"
            }
          },
          {
            "id": "ce24617f706e980c",
            "type": "leaf",
            "state": {
              "type": "tag",
              "state": {
                "sortOrder": "frequency",
                "useHierarchy": false,
                "showSearch": false,
                "searchQuery": ""
              },
              "icon": "lucide-tags",
              "title": "Tags"
            }
          },
          {
            "id": "12ae8687aa7ee1d5",
            "type": "leaf",
            "state": {
              "type": "git-view",
              "state": {},
              "icon": "git-pull-request",
              "title": "Source Control"
            }
          },
          {
            "id": "107b4cc5ab26d28a",
            "type": "leaf",
            "state": {
              "type": "backlink",
              "state": {
                "file": "Reason/From Descartes to Darwin; Why God's Existence is an innate concept..md",
                "collapseAll": false,
                "extraContext": false,
                "sortOrder": "alphabetical",
                "showSearch": false,
                "searchQuery": "",
                "backlinkCollapsed": false,
                "unlinkedCollapsed": true
              },
              "icon": "links-coming-in",
              "title": "Backlinks for From Descartes to Darwin; Why God's Existence is an innate concept."
            }
          },
          {
            "id": "ae3971d108ddafb5",
            "type": "leaf",
            "state": {
              "type": "outgoing-link",
              "state": {
                "file": "Reason/From Descartes to Darwin; Why God's Existence is an innate concept..md",
                "linksCollapsed": false,
                "unlinkedCollapsed": true
              },
              "icon": "links-going-out",
              "title": "Outgoing links from From Descartes to Darwin; Why God's Existence is an innate concept."
            }
          },
          {
            "id": "07272588c94fc352",
            "type": "leaf",
            "state": {
              "type": "outline",
              "state": {
                "file": "Reason/From Descartes to Darwin; Why God's Existence is an innate concept..md",
                "followCursor": false,
                "showSearch": false,
                "searchQuery": ""
              },
              "icon": "lucide-list",
              "title": "Outline of From Descartes to Darwin; Why God's Existence is an innate concept."
            }
          }
        ],
        "currentTab": 2
      },
      {
        "id": "1e4f8f703f5341f0",
        "type": "tabs",
        "dimension": 50.692225772097984,
        "children": [
          {
            "id": "67ef2c190d841bcf",
            "type": "leaf",
            "state": {
              "type": "calendar",
              "state": {},
              "icon": "calendar-with-checkmark",
              "title": "Calendar"
            }
          }
        ]
      }
    ],
    "direction": "horizontal",
    "width": 267.5
  },
  "left-ribbon": {
    "hiddenItems": {
      "command-palette:Open command palette": false,
      "graph:Open graph view": false,
      "switcher:Open quick switcher": true,
      "canvas:Create new canvas": false,
      "daily-notes:Open today's daily note": true,
      "templates:Insert template": true,
      "workspaces:Manage workspace layouts": true,
      "obsidian-kanban:Create new board": false,
      "bases:Create new base": false,
      "obsidian-git:Open Git source control": false,
      "terminal:Open terminal": false
    }
  },
  "active": "782a0ab928ab5810",
  "lastOpenFiles": [
    "History/People/BIO - Jacob Bernoulli.md",
    "History/_History - Map of Contents.md",
    "History/People/BIO - Ibn Sina.md",
    "History/People/BIO - Al-Ghazali.md",
    "GEMINI.md",
    "History/Contemporary",
    "History/Medieval",
    "Science/Computer Science/Projects/Chevreul's Raster Imaging System.md",
    "Science/Computer Science/Projects/AVALsys n8n workflow.md",
    "Reason/Ibn Sina to Al-Ghazli to Ibn Rushd; The evolution of Metaphysics in Islam's Intellectual History.md",
    "Reason/The Julian Star and Intellectualism as a Category of People..md",
    "Reason/An Effort to understand Iqbal.md",
    "History/People/BIO - Galileo Galilei.md",
    "History/People/BIO - Euclid.md",
    "History/People/BIO - Euler.md",
    "History/Medieval/The Holy Roman Empire/EMP - The Holy Roman Empire.md",
    "History/Medieval/The Holy Roman Empire/HIST - Bohemia and Charles IV.md",
    "History/Medieval/The Holy Roman Empire/HIST - King Sigismund and Bohemia.md",
    "History/Medieval/The Holy Roman Empire/HIST - The Great Western Schism.md",
    "Reason/Chain Of Thoughts.md",
    "Reason/From Descartes to Darwin; Why God's Existence is an innate concept..md",
    "History/People/BIO - Ibn e Sina.md",
    "Science/Computer Science/Web-Dev/WEB - Comparison of Node, Next, and React.js.md",
    "Science/Computer Science/Web-Dev/WEB - JavaScript Frameworks.md",
    "Science/Computer Science/Web-Dev/WEB - JavaScript Frameworks.md",
    "Science/Computer Science/Projects",
    "Science/Computer Science/CS - Software Design Techniques.md",
    "Science/Computer Science/Web-Dev/WEB - Evolution of Web Development.md",
    "Science/Computer Science/Dev",
    "Science/Computer Science/Dev/CS - Comparison of Node, Next, and React.js.md",
    "tmp/attachments",
    "tmp",
    "Literature/Books/Ovid's-Metamorphosis.pdf",
    "Science/Mathematics/Geometry",
    "Reason/Epistemology",
    "Reason/Ethics",
    "Art/paintings_source/School_Of_Athens.webp",
    "Untitled.canvas",
    "Arts/paintings_source/A_Sunday Afternoon_on_the Island_of_La Grande_Jatte.webp",
    "Art/paintings_source/A_Sunday Afternoon_on_the Island_of_La Grande_Jatte.png",
    "did-you-know-The-School-of-Athens-Raphael.webp",
    "Arts/paintings_source/A_Sunday Afternoon_on_the Island_of_La Grande_Jatte 1.webp",
    "Pasted image 20251225213804.png",
    "Arts/paintings_source/A_Sunday Afternoon_on_the Island_of_La Grande_Jatte..jpg",
    "did-you-know-The-School-of-Athens-Raphael 2.webp",
    "did-you-know-The-School-of-Athens-Raphael 1.webp",
    "The Grounded Study/Science/Untitled Diagram.svg",
    "Untitled 1.canvas"
  ]
}